investimentos/__init__.py
investimentos/investimentos.py
meu_investimento_acr-0.1.dist-info/licenses/LICENCE
meu_investimento_acr-0.1.dist-info/METADATA
meu_investimento_acr-0.1.dist-info/WHEEL
meu_investimento_acr-0.1.dist-info/top_level.txt
meu_investimento_acr-0.1.dist-info/RECORD
