Metadata-Version: 2.4
Name: meu_investimento_ACR
Version: 0.1
Summary: Uma biblioteca para cálculos de investimentos.
Home-page: https://github.com/AngeloCRossi/MLET_PYTHON_ML_IA_AULA2.git
Author: Angelo Rossi
Author-email: yrc_legna@hotmail.com
Classifier: Programming Language :: Python :: 3
Classifier: License :: OSI Approved :: MIT License
Classifier: Operating System :: OS Independent
Requires-Python: >=3.6
License-File: LICENCE
Dynamic: author
Dynamic: author-email
Dynamic: classifier
Dynamic: home-page
Dynamic: license-file
Dynamic: requires-python
Dynamic: summary
